advanced_random/__init__.py
advanced_random/advanced_random.py
advanced_random-0.1.0.dist-info/licenses/LICENSE
advanced_random-0.1.0.dist-info/METADATA
advanced_random-0.1.0.dist-info/WHEEL
advanced_random-0.1.0.dist-info/top_level.txt
advanced_random-0.1.0.dist-info/RECORD
