Metadata-Version: 2.4
Name: advanced-random
Version: 0.1.0
Summary: Расширенная библиотека для генерации случайных значений в Python
Home-page: https://github.com/Timer-sigma/AdvancedRandom
Author: DarkIce
Author-email: mygopgopich@gmail.com
Project-URL: Source, https://github.com/Timer-sigma/AdvancedRandom
Project-URL: Bug Reports, https://github.com/Timer-sigma/AdvancedRandom
Keywords: random,advanced,utility,generator,weighted,password
Classifier: Programming Language :: Python :: 3
Classifier: License :: OSI Approved :: MIT License
Classifier: Operating System :: OS Independent
Requires-Python: >=3.6
License-File: LICENSE
Dynamic: author
Dynamic: author-email
Dynamic: classifier
Dynamic: description
Dynamic: description-content-type
Dynamic: home-page
Dynamic: keywords
Dynamic: license-file
Dynamic: project-url
Dynamic: requires-python
Dynamic: summary
